MalwareClassifier/__init__.py
MalwareClassifier/_version.py
MalwareClassifier/config.json
MalwareClassifier/logging.py
MalwareClassifier/malware_classifier.py
malwareclassifier-0.1.5.dist-info/licenses/LICENSE
malwareclassifier-0.1.5.dist-info/METADATA
malwareclassifier-0.1.5.dist-info/WHEEL
malwareclassifier-0.1.5.dist-info/top_level.txt
malwareclassifier-0.1.5.dist-info/RECORD
