Metadata-Version: 2.4
Name: MalwareClassifier
Version: 0.1.5
Summary: A malware classifier template with built-in logging.
Author-email: cchunhuang <cchunhuang147@gmail.com>
License: MIT License
Project-URL: Homepage, https://github.com/cchunhuang/MalwareClassifier
Project-URL: Issues, https://github.com/cchunhuang/MalwareClassifier/issues
Classifier: Programming Language :: Python :: 3
Classifier: License :: OSI Approved :: MIT License
Classifier: Operating System :: OS Independent
Requires-Python: >=3.8
License-File: LICENSE
Requires-Dist: python_box>=7.3.2
Requires-Dist: python-json-logger>=2.0.7
Dynamic: license-file
